setup.py
rediset/__init__.py
rediset/api.py
rediset/base.py
rediset/sets.py
rediset/sortedsets.py
rediset.egg-info/PKG-INFO
rediset.egg-info/SOURCES.txt
rediset.egg-info/dependency_links.txt
rediset.egg-info/requires.txt
rediset.egg-info/top_level.txt