Metadata-Version: 1.0
Name: rediset
Version: 0.12.0
Summary: Composable, cacheable, lazy trees of Redis set operations
Home-page: https://github.com/j4mie/rediset
Author: Jamie Matthews
Author-email: jamie.matthews@gmail.com
License: Public Domain
Platform: UNKNOWN
Classifier: Programming Language :: Python
Classifier: Development Status :: 3 - Alpha
Classifier: Intended Audience :: Developers
Classifier: License :: Public Domain
Classifier: Operating System :: MacOS :: MacOS X
Classifier: Topic :: Software Development :: Libraries :: Python Modules
Classifier: Topic :: Database
Classifier: Topic :: Database :: Front-Ends
